{
  "$schema": "https://raw.githubusercontent.com/electron-userland/electron-builder/refs/heads/master/packages/app-builder-lib/scheme.json",
  "compression": "maximum",
  "artifactName": "${productName}-${os}-${arch}-${version}.${ext}",
  "linux": {
    "target": ["tar.xz"],
    "executableArgs": ["--no-sandbox"],
    "category": "Game",
    "icon": "Packaging/flatpak/dev.hyprism.HyPrism.png",
    "maintainer": "HyPrism Team <noreply@example.com>"
  },
  "win": {
    "target": ["zip"],
    "icon": "Packaging/windows/HyPrism.ico"
  },
  "mac": {
    "target": ["dmg"],
    "category": "public.app-category.games",
    "icon": "Packaging/macos/hyprism-macos.icns"
  }
}
